kabbes_imessage/Message.py
kabbes_imessage/Messages.py
kabbes_imessage/PhoneNumber.py
kabbes_imessage/PhoneNumbers.py
kabbes_imessage/__init__.py
kabbes_imessage/__main__.py
kabbes_imessage/message_mediums/SMS.applescript
kabbes_imessage/message_mediums/iMessage.applescript
kabbes_imessage-0.1.0.dist-info/LICENSE
kabbes_imessage-0.1.0.dist-info/METADATA
kabbes_imessage-0.1.0.dist-info/WHEEL
kabbes_imessage-0.1.0.dist-info/top_level.txt
kabbes_imessage-0.1.0.dist-info/RECORD
