Metadata-Version: 2.1
Name: kabbes-imessage
Version: 0.1.0
Summary: Python tools for sending iMessages on a Mac
Home-page: https://pypi.org/project/kabbes-imessage/
Author: James Kabbes
Author-email: james.kabbes@gmail.com
Project-URL: GitHub, https://github.com/jameskabbes/imessage
Project-URL: Documentation, https://jameskabbes.github.io/imessage
Classifier: Programming Language :: Python :: 3
Classifier: License :: OSI Approved :: MIT License
Classifier: Operating System :: OS Independent
Requires-Python: >=3.7
License-File: LICENSE
Requires-Dist: kabbes-dir-ops
Requires-Dist: kabbes-parent-class
Requires-Dist: kabbes-py-starter
